frozenlist-1.6.1.dist-info/RECORD
frozenlist-1.6.1.dist-info/WHEEL
frozenlist-1.6.1.dist-info/top_level.txt
frozenlist-1.6.1.dist-info/METADATA
frozenlist-1.6.1.dist-info/licenses/LICENSE
frozenlist/__init__.pyi
frozenlist/__init__.py
frozenlist/_frozenlist.pyx
frozenlist/py.typed
frozenlist/_frozenlist.cpython-310-darwin.so
