Metadata-Version: 2.4
Name: frozenlist
Version: 1.6.1
Summary: A list-like structure which implements collections.abc.MutableSequence
Home-page: https://github.com/aio-libs/frozenlist
Maintainer: aiohttp team <team@aiohttp.org>
Maintainer-email: team@aiohttp.org
License: Apache-2.0
Project-URL: Chat: Matrix, https://matrix.to/#/#aio-libs:matrix.org
Project-URL: Chat: Matrix Space, https://matrix.to/#/#aio-libs-space:matrix.org
Project-URL: CI: Github Actions, https://github.com/aio-libs/frozenlist/actions
Project-URL: Code of Conduct, https://github.com/aio-libs/.github/blob/master/CODE_OF_CONDUCT.md
Project-URL: Coverage: codecov, https://codecov.io/github/aio-libs/frozenlist
Project-URL: Docs: Changelog, https://github.com/aio-libs/frozenlist/blob/master/CHANGES.rst#changelog
Project-URL: Docs: RTD, https://frozenlist.aio-libs.org
Project-URL: GitHub: issues, https://github.com/aio-libs/frozenlist/issues
Project-URL: GitHub: repo, https://github.com/aio-libs/frozenlist
Classifier: Development Status :: 5 - Production/Stable
Classifier: Intended Audience :: Developers
Classifier: Operating System :: POSIX
Classifier: Operating System :: MacOS :: MacOS X
Classifier: Operating System :: Microsoft :: Windows
Classifier: Programming Language :: Cython
Classifier: Programming Language :: Python
Classifier: Programming Language :: Python :: 3
Classifier: Programming Language :: Python :: 3.9
Classifier: Programming Language :: Python :: 3.10
Classifier: Programming Language :: Python :: 3.11
Classifier: Programming Language :: Python :: 3.12
Classifier: Programming Language :: Python :: 3.13
Classifier: Programming Language :: Python :: Implementation :: CPython
Classifier: Programming Language :: Python :: Implementation :: PyPy
Requires-Python: >=3.9
License-File: LICENSE
Dynamic: license-file
